ai_chat_html_exporter/__init__.py
ai_chat_html_exporter/html_generator.py
ai_chat_html_exporter/langchain_chat_html_exporter.py
ai_chat_html_exporter/openai_chat_html_exporter.py
ai_chat_html_exporter-1.0.3.post1.dist-info/licenses/LICENSE
ai_chat_html_exporter-1.0.3.post1.dist-info/METADATA
ai_chat_html_exporter-1.0.3.post1.dist-info/WHEEL
ai_chat_html_exporter-1.0.3.post1.dist-info/top_level.txt
ai_chat_html_exporter-1.0.3.post1.dist-info/RECORD
