Metadata-Version: 2.4
Name: ai_chat_html_exporter
Version: 1.0.3.post1
Summary: A tool to export AI chat history to HTML with syntax highlighting
Home-page: https://github.com/fishisnow/ai-chat-html-exporter
Author: fishisnow
Author-email: fishisnow2021@gmail.com
Classifier: Programming Language :: Python :: 3
Classifier: License :: OSI Approved :: MIT License
Classifier: Operating System :: OS Independent
Requires-Python: >=3.12
License-File: LICENSE
Requires-Dist: langchain-core>=0.3.0
Requires-Dist: python-dotenv>=1.0.0
Requires-Dist: openai>=1.6.1
Dynamic: author
Dynamic: author-email
Dynamic: classifier
Dynamic: description
Dynamic: description-content-type
Dynamic: home-page
Dynamic: license-file
Dynamic: requires-dist
Dynamic: requires-python
Dynamic: summary
